mageArmor/__init__.py
mageArmor/mageArmor.py
mageArmor-0.2.dist-info/LICENSE
mageArmor-0.2.dist-info/METADATA
mageArmor-0.2.dist-info/WHEEL
mageArmor-0.2.dist-info/top_level.txt
mageArmor-0.2.dist-info/RECORD
