Metadata-Version: 2.1
Name: mageArmor
Version: 0.2
Summary: Ferramenta de proteção contra prompt injection
Home-page: https://github.com/s2Alive/mageArmor
Author: Rodrigo Correia Santos, Gustavo Santos Rocha
Author-email: contato.rodrigocorreiaba753@outlook.com.br, contato.gsr13@gmail.com
Classifier: Programming Language :: Python :: 3
Classifier: License :: OSI Approved :: MIT License
Classifier: Operating System :: OS Independent
Requires-Python: >=3.6
License-File: LICENSE
